Metadata-Version: 1.1
Name: django-datastream
Version: 0.2.1
Summary: Django HTTP interface to Datastream API time-series library.
Home-page: https://github.com/wlanslovenija/django-datastream
Author: wlan slovenija
Author-email: open@wlan-si.net
License: AGPLv3
Platform: UNKNOWN
Classifier: Development Status :: 4 - Beta
Classifier: Environment :: Web Environment
Classifier: Intended Audience :: Developers
Classifier: License :: OSI Approved :: GNU Affero General Public License v3
Classifier: Operating System :: OS Independent
Classifier: Programming Language :: Python
Classifier: Framework :: Django
